Oasys/THIS/__init__.py
Oasys/THIS/colour.py
Oasys/THIS/component.py
Oasys/THIS/constant.py
Oasys/THIS/core.py
Oasys/THIS/curve.py
Oasys/THIS/datum.py
Oasys/THIS/entity.py
Oasys/THIS/funcs.py
Oasys/THIS/graph.py
Oasys/THIS/group.py
Oasys/THIS/itemobject.py
Oasys/THIS/linestyle.py
Oasys/THIS/linewidth.py
Oasys/THIS/model.py
Oasys/THIS/operate.py
Oasys/THIS/options.py
Oasys/THIS/page.py
Oasys/THIS/read.py
Oasys/THIS/symbol.py
Oasys/THIS/units.py
Oasys/THIS/unitsystem.py
Oasys/THIS/utils.py
Oasys/THIS/window.py
Oasys/THIS/workflow.py
oasys_this-22.1.0.dist-info/licenses/LICENSE
oasys_this-22.1.0.dist-info/METADATA
oasys_this-22.1.0.dist-info/WHEEL
oasys_this-22.1.0.dist-info/top_level.txt
oasys_this-22.1.0.dist-info/RECORD
