Metadata-Version: 2.4
Name: Oasys.THIS
Version: 22.1.0
Summary: Python API for Oasys T/HIS
Author: Miles Thornton
Maintainer-email: DYNA support <dyna.support@arup.com>
Project-URL: Documentation, https://help.oasys-software.com/resources/Storage/sphinx/22.1/T-HIS/index.html
Project-URL: Homepage, https://www.oasys-software.com/dyna/software/t-his/
Project-URL: Linkedin, https://www.linkedin.com/company/oasys-ltd-software/
Project-URL: YouTube, https://www.youtube.com/c/OasysLtd
Keywords: Oasys,THIS,T/HIS
Requires-Python: >=3.8
License-File: LICENSE
Requires-Dist: Oasys.gRPC~=22.0.0
Dynamic: license-file
